{
	"archive" : {},
	"artifacts" : 
	[
		{
			"path" : "src/Lights/libLights.a"
		}
	],
	"backtrace" : 1,
	"backtraceGraph" : 
	{
		"commands" : 
		[
			"add_library",
			"target_include_directories"
		],
		"files" : 
		[
			"src/Lights/CMakeLists.txt"
		],
		"nodes" : 
		[
			{
				"file" : 0
			},
			{
				"command" : 0,
				"file" : 0,
				"line" : 1,
				"parent" : 0
			},
			{
				"command" : 1,
				"file" : 0,
				"line" : 2,
				"parent" : 0
			}
		]
	},
	"compileGroups" : 
	[
		{
			"compileCommandFragments" : 
			[
				{
					"fragment" : "-g  "
				}
			],
			"includes" : 
			[
				{
					"backtrace" : 2,
					"path" : "/home/matt/Documents/Programming/rendering-engine/src/Lights"
				}
			],
			"language" : "CXX",
			"sourceIndexes" : 
			[
				0
			]
		}
	],
	"id" : "Lights::@d2fa95cb4f58df5f05d4",
	"name" : "Lights",
	"nameOnDisk" : "libLights.a",
	"paths" : 
	{
		"build" : "src/Lights",
		"source" : "src/Lights"
	},
	"sourceGroups" : 
	[
		{
			"name" : "Source Files",
			"sourceIndexes" : 
			[
				0
			]
		}
	],
	"sources" : 
	[
		{
			"backtrace" : 1,
			"compileGroupIndex" : 0,
			"path" : "src/Lights/pointlight.cpp",
			"sourceGroupIndex" : 0
		}
	],
	"type" : "STATIC_LIBRARY"
}
